{"is_source_file": true, "description": "Simple txt file", "external_files": [], "external_methods": [], "published": [], "calls": [], "search-terms": [], "classes": [], "methods": [], "state": 2, "file_id": 6, "knowledge_revision": 14, "git_revision": "db62847b13e25e13988b7604deb3f136f7eb77e5", "filename": "notes_backend/requirements.txt", "hash": "8c00f29dbd6c22720eba7f783fb58776", "format-version": 4, "code-base-name": "https://github.com/kavia-common/personal-notes-organizer-10316-10336.git:kavia-main", "revision_history": [{"14": "db62847b13e25e13988b7604deb3f136f7eb77e5"}]}